humanllm/__about__.py
humanllm/__init__.py
humanllm-0.0.1.dist-info/METADATA
humanllm-0.0.1.dist-info/WHEEL
humanllm-0.0.1.dist-info/licenses/LICENSE.txt
humanllm-0.0.1.dist-info/RECORD
