Metadata-Version: 2.1
Name: humanllm
Version: 0.0.1
Summary: LLMs for humans
Project-URL: Documentation, https://github.com/unknown/humanllm#readme
Project-URL: Issues, https://github.com/unknown/humanllm/issues
Project-URL: Source, https://github.com/unknown/humanllm
Author-email: Jian Yuan Lee <jianyuan@gmail.com>
License-Expression: MIT
License-File: LICENSE.txt
Classifier: Development Status :: 4 - Beta
Classifier: Programming Language :: Python
Classifier: Programming Language :: Python :: 3.7
Classifier: Programming Language :: Python :: 3.8
Classifier: Programming Language :: Python :: 3.9
Classifier: Programming Language :: Python :: 3.10
Classifier: Programming Language :: Python :: 3.11
Classifier: Programming Language :: Python :: Implementation :: CPython
Classifier: Programming Language :: Python :: Implementation :: PyPy
Requires-Python: >=3.7
